azure/mgmt/imagebuilder/__init__.py
azure/mgmt/imagebuilder/_configuration.py
azure/mgmt/imagebuilder/_image_builder_client.py
azure/mgmt/imagebuilder/_patch.py
azure/mgmt/imagebuilder/_serialization.py
azure/mgmt/imagebuilder/_vendor.py
azure/mgmt/imagebuilder/_version.py
azure/mgmt/imagebuilder/py.typed
azure/mgmt/imagebuilder/aio/__init__.py
azure/mgmt/imagebuilder/aio/_configuration.py
azure/mgmt/imagebuilder/aio/_image_builder_client.py
azure/mgmt/imagebuilder/aio/_patch.py
azure/mgmt/imagebuilder/aio/operations/__init__.py
azure/mgmt/imagebuilder/aio/operations/_operations.py
azure/mgmt/imagebuilder/aio/operations/_patch.py
azure/mgmt/imagebuilder/aio/operations/_triggers_operations.py
azure/mgmt/imagebuilder/aio/operations/_virtual_machine_image_templates_operations.py
azure/mgmt/imagebuilder/models/__init__.py
azure/mgmt/imagebuilder/models/_image_builder_client_enums.py
azure/mgmt/imagebuilder/models/_models_py3.py
azure/mgmt/imagebuilder/models/_patch.py
azure/mgmt/imagebuilder/operations/__init__.py
azure/mgmt/imagebuilder/operations/_operations.py
azure/mgmt/imagebuilder/operations/_patch.py
azure/mgmt/imagebuilder/operations/_triggers_operations.py
azure/mgmt/imagebuilder/operations/_virtual_machine_image_templates_operations.py
azure_mgmt_imagebuilder-1.4.0.dist-info/LICENSE
azure_mgmt_imagebuilder-1.4.0.dist-info/METADATA
azure_mgmt_imagebuilder-1.4.0.dist-info/WHEEL
azure_mgmt_imagebuilder-1.4.0.dist-info/top_level.txt
azure_mgmt_imagebuilder-1.4.0.dist-info/RECORD
